{
  "updated": "2026-05-08T07:45:07.708Z",
  "feeds": {
    "moneystruggles": [
      {
        "id": "18457089883110043",
        "url": "https://www.instagram.com/p/DYDkmeOgPcq/",
        "caption": "A lot of people are quietly realizing that surviving on one income today feels very different than i"
      },
      {
        "id": "17902574030741605",
        "url": "https://www.instagram.com/p/CpOyRyCLDEM/",
        "caption": "People who do not have adequate financial resources face immense challenges. The stress that comes f"
      },
      {
        "id": "18111007345661511",
        "url": "https://www.instagram.com/p/DXm7RnOm6ie/",
        "caption": "Seriously, is this just how life feels now or do people actually reach a point where money stops fee"
      }
    ],
    "worklife": [
      {
        "id": "18006008801819001",
        "url": "https://www.instagram.com/p/DSTi8EpDxk5/",
        "caption": "feeing seen 😂😂 tvmoments"
      },
      {
        "id": "18446694628106833",
        "url": "https://www.instagram.com/p/DTT9CQVk9it/",
        "caption": "After factoring in prices and hours worked, Singapore falls to eighth place on The Economist's ranki"
      },
      {
        "id": "18104878822938858",
        "url": "https://www.instagram.com/p/DX51_UZjqeX/",
        "caption": "If you've ever worked for someone like Miranda Priestly, you get it. Having a boss who is never impr"
      }
    ],
    "adulting": [
      {
        "id": "18144982294462474",
        "url": "https://www.instagram.com/p/DUZfiN_EQ-C/",
        "caption": "Hay días en los que haces todo bien\ny aun así no pasa nada.\n\nTrabajas, entrenas, duermes…\no algo par"
      },
      {
        "id": "18330193138246308",
        "url": "https://www.instagram.com/p/DS6Pk5-FANN/",
        "caption": "Ahh not a single unique experience beingalibertarian"
      },
      {
        "id": "17865735351545947",
        "url": "https://www.instagram.com/p/DYCdt5DmbKd/",
        "caption": "We didn’t get here easily, but we got here together ❤️\nWallet kosong, but house secured 🏠 \nHouse is"
      }
    ],
    "adultfreedom": [
      {
        "id": "17899893340476979",
        "url": "https://www.instagram.com/p/CBI95ZSlq0n/",
        "caption": "Sorry mum"
      },
      {
        "id": "18392559208120302",
        "url": "https://www.instagram.com/p/DQrOd02Exrl/",
        "caption": "🛳️ I’m not escaping anything. I’m just giving myself permission to pause, to breathe, to be human a"
      },
      {
        "id": "18109880746582615",
        "url": "https://www.instagram.com/p/DQIEMjJkVvk/",
        "caption": "Respect to all first responders; especially the ones with diaper bags.\n\n#NoKidsClub #AdultFreedom #C"
      }
    ],
    "relationshipstruggles": [
      {
        "id": "18050938810976303",
        "url": "https://www.instagram.com/p/DC_MhJnR6Bo/",
        "caption": "🤷🏾‍♂️🤷🏾‍♂️🤷🏾‍♂️\n\n#letthemgo #healingafterdivorce #healing #relationshipstruggles #exes #exrela"
      },
      {
        "id": "18038613116238535",
        "url": "https://www.instagram.com/p/DCDfafrPdhI/",
        "caption": "The events that happened in your past cannot be changed…\n\nHowever, how you choose to move forward, i"
      },
      {
        "id": "18072782096082366",
        "url": "https://www.instagram.com/p/DNOeZQ_SGKD/",
        "caption": "If your relationship feels like you’re constantly swimming upstream despite understanding each other"
      }
    ],
    "adultingishard": [
      {
        "id": "17986611206353534",
        "url": "https://www.instagram.com/p/Cwyz8z1oKoG/",
        "caption": "👱‍♀️👩‍🦰💆‍♀️💆‍♂️👩‍🦱👩‍🦳👨‍🦳 \n#memes #therealshitgyan #explore #explorepageready #explorepage"
      },
      {
        "id": "17981661989638260",
        "url": "https://www.instagram.com/p/C4WucOUSuoM/",
        "caption": "Do re mi fa old.\n\n#procreate #comicpage #comicpanel #digitalcomic #webcomics #webtoon #webtoons #doo"
      },
      {
        "id": "18158472430389224",
        "url": "https://www.instagram.com/p/DPXOo82CTN2/",
        "caption": "If this isn’t the perfect metaphor for adulthood, I don’t know what is ;)\n\n▸ All rights and credit r"
      }
    ],
    "findingpurpose": [
      {
        "id": "17856290968570269",
        "url": "https://www.instagram.com/p/B3TI_T5l3Lb/",
        "caption": "How Jayla got her groove back🖤 ⁣\n⁣\nLately I’ve had postpartum struggles. It’s something I’m open ab"
      },
      {
        "id": "18048513553128655",
        "url": "https://www.instagram.com/p/BxP_SIfH2id/",
        "caption": "In the last few months we have been trying to push ourselves through and challenge all that we can r"
      },
      {
        "id": "18025932946520678",
        "url": "https://www.instagram.com/p/CsEI_gWOB3L/",
        "caption": "This month will be the seven year anniversary of my walking into kellybroganmd office and into a bra"
      }
    ]
  }
}