{
  "updated": "2026-04-04T07:04:55.432Z",
  "feeds": {
    "moneystruggles": [
      {
        "id": "18033803668180444",
        "url": "https://www.instagram.com/p/BxazoAEhHzL/",
        "caption": "Let’s talk about MONEY/finances because Financial Wellness is one of the 8 pillars of Holistic Healt"
      },
      {
        "id": "17902574030741605",
        "url": "https://www.instagram.com/p/CpOyRyCLDEM/",
        "caption": "People who do not have adequate financial resources face immense challenges. The stress that comes f"
      },
      {
        "id": "18095465431333135",
        "url": "https://www.instagram.com/p/CtMVkLzszDP/",
        "caption": "The biggest obstacles to budgeting are not what you think.⁠\n⁠\nAre you struggling to keep up with you"
      }
    ],
    "worklife": [
      {
        "id": "17858550510627039",
        "url": "https://www.instagram.com/p/DWrTWPBFJcT/",
        "caption": "Happy Friday 🤞🏾✨\n\n#explore #fridayvibes #explorepage✨ #relatable #worklife"
      },
      {
        "id": "18025179038773118",
        "url": "https://www.instagram.com/p/DPluD_JkYgq/",
        "caption": "(Very important) the.language.nerds"
      },
      {
        "id": "17871724641455838",
        "url": "https://www.instagram.com/p/DVy3z8RCeXE/",
        "caption": "My favorite sticker is “KTA” (Knew The Acronym) and I wear it every day corporate.jargon \n\nWhich sti"
      }
    ],
    "adulting": [
      {
        "id": "18025179038773118",
        "url": "https://www.instagram.com/p/DPluD_JkYgq/",
        "caption": "(Very important) the.language.nerds"
      },
      {
        "id": "17944489398045604",
        "url": "https://www.instagram.com/p/DOJc8SpEo0g/",
        "caption": "FOLLOW bitchyquotes for more hilarious & relatable memes 🤣 👉bitchyquotes bitchyquotes 👈🤣"
      },
      {
        "id": "18330193138246308",
        "url": "https://www.instagram.com/p/DS6Pk5-FANN/",
        "caption": "Ahh not a single unique experience beingalibertarian"
      }
    ],
    "adultfreedom": [
      {
        "id": "17899893340476979",
        "url": "https://www.instagram.com/p/CBI95ZSlq0n/",
        "caption": "Sorry mum"
      },
      {
        "id": "18015455044021466",
        "url": "https://www.instagram.com/p/Br1au9VH6z_/",
        "caption": "By this time of the night we were both burnt out. Photos just got weird and the Disney photo team ad"
      },
      {
        "id": "18001549177083918",
        "url": "https://www.instagram.com/p/Bs3-XlGHW3D/",
        "caption": "Chillin at the UK in Disney, and the wife says” Drink some water Shaughn” after our 3rd stop on the "
      }
    ],
    "relationshipstruggles": [
      {
        "id": "18064278994387003",
        "url": "https://www.instagram.com/p/CsSuWbSoOje/",
        "caption": "Say it again! 💯 \n\n#facts #relationshipstruggles #tweet #lovelife #couplequotes #feelings #hurtful"
      },
      {
        "id": "17922289541765355",
        "url": "https://www.instagram.com/p/C22bhq-sr_G/",
        "caption": "Follow for more\n.\n. daily relationship and love quotes 💕\n.\n.\n.\n#setboundaries #startingoverquotes #"
      },
      {
        "id": "18047475308497600",
        "url": "https://www.instagram.com/p/DCkz8bNPHDM/",
        "caption": "It’s a harsh reality… 😔\n\nBut a relationship without safety… unfortunately, does not stand a chance "
      }
    ],
    "adultingishard": [
      {
        "id": "18007546220434062",
        "url": "https://www.instagram.com/p/C6RLssrNNLF/",
        "caption": "For years it drove me crazy that Casey would walk by the sink, see the pile of dishes and not wash t"
      },
      {
        "id": "17986611206353534",
        "url": "https://www.instagram.com/p/Cwyz8z1oKoG/",
        "caption": "👱‍♀️👩‍🦰💆‍♀️💆‍♂️👩‍🦱👩‍🦳👨‍🦳 \n#memes #therealshitgyan #explore #explorepageready #explorepage"
      },
      {
        "id": "18241633507250271",
        "url": "https://www.instagram.com/p/C8CZdnAAsBi/",
        "caption": "🤡"
      }
    ],
    "findingpurpose": [
      {
        "id": "17856290968570269",
        "url": "https://www.instagram.com/p/B3TI_T5l3Lb/",
        "caption": "How Jayla got her groove back🖤 ⁣\n⁣\nLately I’ve had postpartum struggles. It’s something I’m open ab"
      },
      {
        "id": "17927259769284619",
        "url": "https://www.instagram.com/p/BvNbiFgABKr/",
        "caption": "Dear Babygirl,\nI’m so proud of YOU. All that you have overcome because of your belief in God. All th"
      },
      {
        "id": "17990061140067610",
        "url": "https://www.instagram.com/p/CwXt-NQuOD1/",
        "caption": "If you’re curious to go deeper into your exploration of purpose, you’ll find a lot of value in the “"
      }
    ]
  }
}